setup.py
pocket/__init__.py
pocket/database.py
pocket/log_lib.py
sneeze_pocket.egg-info/PKG-INFO
sneeze_pocket.egg-info/SOURCES.txt
sneeze_pocket.egg-info/dependency_links.txt
sneeze_pocket.egg-info/entry_points.txt
sneeze_pocket.egg-info/requires.txt
sneeze_pocket.egg-info/top_level.txt