Metadata-Version: 1.1
Name: sneeze-pocket
Version: 0.0.1
Summary: A Sneeze plugin for logging logging
Home-page: http://pocket.readthedocs.org/
Author: Silas Ray
Author-email: silas.ray@nytimes.com
License: Apache2.0
Platform: UNKNOWN
Classifier: Development Status :: 4 - Beta
Classifier: Intended Audience :: Information Technology
Classifier: Topic :: Software Development :: Quality Assurance
Classifier: Topic :: Software Development :: Testing
